elanwrapper/__init__.py
elanwrapper/conflicts.py
elanwrapper/preferences.py
elanwrapper/segments.py
elanwrapper/wrapper.py
tests/__init__.py
tests/test_elan_file.py
tests/test_timeline.py
elanwrapper-1.0.0a1.dist-info/METADATA
elanwrapper-1.0.0a1.dist-info/WHEEL
elanwrapper-1.0.0a1.dist-info/top_level.txt
elanwrapper-1.0.0a1.dist-info/RECORD
