Metadata-Version: 2.1
Name: elanwrapper
Version: 1.0.0a1
Author: PALAT Labs
Requires-Python: >=3.7
Requires-Dist: pympi-ling (>=1.69)
Requires-Dist: sortedcontainers (>=2.4.0)
